setup.py
nd_bd_probability_pkg/Binomialdistribution.py
nd_bd_probability_pkg/Gaussiandistribution.py
nd_bd_probability_pkg/Generaldistribution.py
nd_bd_probability_pkg/__init__.py
nd_bd_probability_pkg.egg-info/PKG-INFO
nd_bd_probability_pkg.egg-info/SOURCES.txt
nd_bd_probability_pkg.egg-info/dependency_links.txt
nd_bd_probability_pkg.egg-info/not-zip-safe
nd_bd_probability_pkg.egg-info/top_level.txt