Metadata-Version: 1.0
Name: nd-bd-probability-pkg
Version: 0.2
Summary: Gaussian and Binomial Distribution
Home-page: UNKNOWN
Author: Kanushka Jayakody
Author-email: kanushkaj@gmail.com
License: UNKNOWN
Platform: UNKNOWN
